settings_overrider.py
settings_overrider-1.0.0.dist-info/LICENSE.mit
settings_overrider-1.0.0.dist-info/METADATA
settings_overrider-1.0.0.dist-info/WHEEL
settings_overrider-1.0.0.dist-info/top_level.txt
settings_overrider-1.0.0.dist-info/RECORD
