Metadata-Version: 2.1
Name: settings-overrider
Version: 1.0.0
Summary: Override Python dict contents with YAML file and/or environment variables
Home-page: https://github.com/kottenator/settings-overrider
Author: Rostyslav Bryzgunov
Author-email: kottenator@gmail.com
License: MIT
Platform: UNKNOWN
Classifier: Intended Audience :: Developers
Classifier: License :: OSI Approved :: MIT License
Classifier: Operating System :: OS Independent
Classifier: Programming Language :: Python :: 2
Classifier: Programming Language :: Python :: 3
License-File: LICENSE.mit
Requires-Dist: PyYAML
Provides-Extra: test
Requires-Dist: pytest ; extra == 'test'
Requires-Dist: pytest-cov ; extra == 'test'
